flask_restful_crud/__init__.py
flask_restful_crud/detail_resource.py
flask_restful_crud/list_resource.py
flask_restful_crud-0.0.1.dist-info/DESCRIPTION.rst
flask_restful_crud-0.0.1.dist-info/METADATA
flask_restful_crud-0.0.1.dist-info/RECORD
flask_restful_crud-0.0.1.dist-info/WHEEL
flask_restful_crud-0.0.1.dist-info/metadata.json
flask_restful_crud-0.0.1.dist-info/top_level.txt
