Metadata-Version: 2.0
Name: flask-restful-crud
Version: 0.0.1
Summary: Bootstrap classes for flask-restful
Home-page: https://bitbucket.org/rysev-a/flask-restful-crud
Author: Rysev Alexei
Author-email: alexeirysev@gmail.com
License: UNKNOWN
Platform: UNKNOWN
Classifier: Programming Language :: Python :: 3.6
Classifier: License :: OSI Approved :: MIT License
Classifier: Operating System :: OS Independent
Requires-Dist: Flask (==1.0.2)
Requires-Dist: Flask-RESTful (==0.3.6)
Requires-Dist: SQLAlchemy (==1.2.9)
